graphql_to_httprunner/__init__.py
graphql_to_httprunner/__main__.py
graphql_to_httprunner/generator.py
graphql_to_httprunner/introspection.py
graphql_to_httprunner/main.py
graphql_to_httprunner/models.py
graphql_to_httprunner/parser.py
graphql_to_httprunner/query_generator.py
graphql_to_httprunner/report_generator.py
graphql_to_httprunner/utils.py
graphql_to_httprunner-1.9.2.dist-info/METADATA
graphql_to_httprunner-1.9.2.dist-info/WHEEL
graphql_to_httprunner-1.9.2.dist-info/entry_points.txt
graphql_to_httprunner-1.9.2.dist-info/RECORD
