Metadata-Version: 2.3
Name: graphql-to-httprunner
Version: 1.9.2
Summary: Automatically generate HttpRunner test cases based on GraphQL Schema
License: MIT
Keywords: graphql,httprunner,api,automation,test
Author: Devin
Author-email: zhangchuzhao@dingtalk.com
Requires-Python: >=3.5
Classifier: Development Status :: 5 - Production/Stable
Classifier: Topic :: Software Development :: Testing
Classifier: Topic :: Software Development :: Quality Assurance
Classifier: Topic :: Software Development :: Libraries :: Python Modules
Classifier: Operating System :: MacOS
Classifier: Operating System :: POSIX :: Linux
Classifier: Operating System :: Microsoft :: Windows
Classifier: Programming Language :: Python :: 3.5
Classifier: Programming Language :: Python :: 3.6
Classifier: Programming Language :: Python :: 3.7
Classifier: Programming Language :: Python :: 3.8
Classifier: Programming Language :: Python :: 3.9
Classifier: Programming Language :: Python :: 3.10
Classifier: Programming Language :: Python :: 3.11
Requires-Dist: pyyaml
Requires-Dist: requests
